pytest_smoke/__init__.py
pytest_smoke/compat.py
pytest_smoke/hooks.py
pytest_smoke/plugin.py
pytest_smoke/py.typed
pytest_smoke/types.py
pytest_smoke/utils.py
pytest_smoke/extensions/__init__.py
pytest_smoke/extensions/xdist.py
pytest_smoke-0.10.0.dist-info/licenses/LICENSE
pytest_smoke-0.10.0.dist-info/METADATA
pytest_smoke-0.10.0.dist-info/WHEEL
pytest_smoke-0.10.0.dist-info/entry_points.txt
pytest_smoke-0.10.0.dist-info/top_level.txt
pytest_smoke-0.10.0.dist-info/RECORD
